[{"date": "20260316", "code": "600396", "name": "华电辽能", "pct": 10.051546096801758, "price": 4.27, "amount": 336687296.0, "float_mkt": 6288458108.589999, "total_mkt": 6288458104.32, "turnover": 5.35405158996582, "sealed_capital": 194499422.0, "first_seal_time": "092500", "last_seal_time": "092500", "explode_count": 0, "continuous": "1/1", "lb_count": 1, "sector": "电力"}, {"date": "20260316", "code": "002086", "name": "东方海洋", "pct": 10.132158279418945, "price": 2.5, "amount": 212411798.0, "float_mkt": 3953215092.5, "total_mkt": 4897366240.0, "turnover": 5.373140335083008, "sealed_capital": 127430167.0, "first_seal_time": "092500", "last_seal_time": "092500", "explode_count": 0, "continuous": "1/1", "lb_count": 1, "sector": "医疗器械"}, {"date": "20260316", "code": "000617", "name": "中油资本", "pct": 10.022522926330566, "price": 9.77, "amount": 4134609392.0, "float_mkt": 123513112601.83, "total_mkt": 123513111595.51999, "turnover": 3.3493659496307373, "sealed_capital": 226347686.0, "first_seal_time": "092500", "last_seal_time": "110933", "explode_count": 5, "continuous": "1/1", "lb_count": 1, "sector": "多元金融"}, {"date": "20260316", "code": "600370", "name": "三房巷", "pct": 9.89011001586914, "price": 3.0, "amount": 500375600.0, "float_mkt": 11690042151.0, "total_mkt": 11690042160.0, "turnover": 4.28670597076416, "sealed_capital": 54804750.0, "first_seal_time": "093002", "last_seal_time": "093008", "explode_count": 1, "continuous": "3/3", "lb_count": 3, "sector": "化学纤维"}, {"date": "20260316", "code": "600227", "name": "赤天化", "pct": 10.068650245666504, "price": 4.81, "amount": 2089693216.0, "float_mkt": 6145255052.429999, "total_mkt": 8122780140.799999, "turnover": 34.47534942626953, "sealed_capital": 28707494.0, "first_seal_time": "093130", "last_seal_time": "144354", "explode_count": 5, "continuous": "7/4", "lb_count": 2, "sector": "农化制品"}, {"date": "20260316", "code": "600302", "name": "标准股份", "pct": 10.038986206054688, "price": 11.29, "amount": 137333517.0, "float_mkt": 3906450687.16, "total_mkt": 3906450732.3199997, "turnover": 3.5572402477264404, "sealed_capital": 51887711.0, "first_seal_time": "093130", "last_seal_time": "093206", "explode_count": 1, "continuous": "1/1", "lb_count": 1, "sector": "专用设备"}, {"date": "20260316", "code": "002310", "name": "东方新能", "pct": 9.926470756530762, "price": 2.99, "amount": 1572789440.0, "float_mkt": 12555158653.830002, "total_mkt": 17937973114.88, "turnover": 12.733926773071289, "sealed_capital": 14955367.0, "first_seal_time": "093236", "last_seal_time": "141151", "explode_count": 8, "continuous": "1/1", "lb_count": 1, "sector": "电力"}, {"date": "20260316", "code": "002427", "name": "尤夫股份", "pct": 10.01430606842041, "price": 7.69, "amount": 284497648.0, "float_mkt": 7572385187.34, "total_mkt": 7577978108.96, "turnover": 3.8151803016662598, "sealed_capital": 100360267.0, "first_seal_time": "093409", "last_seal_time": "093409", "explode_count": 0, "continuous": "1/1", "lb_count": 1, "sector": "化学纤维"}, {"date": "20260316", "code": "600683", "name": "京投发展", "pct": 10.045661926269531, "price": 9.64, "amount": 230542787.0, "float_mkt": 7141096035.080001, "total_mkt": 7141096064.0, "turnover": 3.2924816608428955, "sealed_capital": 124793521.0, "first_seal_time": "093454", "last_seal_time": "093454", "explode_count": 0, "continuous": "2/2", "lb_count": 2, "sector": "房地产开"}, {"date": "20260316", "code": "002278", "name": "神开股份", "pct": 10.0, "price": 13.75, "amount": 517773360.0, "float_mkt": 4592454088.75, "total_mkt": 5363021400.0, "turnover": 11.421939849853516, "sealed_capital": 112314152.0, "first_seal_time": "093509", "last_seal_time": "093509", "explode_count": 0, "continuous": "1/1", "lb_count": 1, "sector": "专用设备"}, {"date": "20260316", "code": "002724", "name": "海洋王", "pct": 10.053619384765625, "price": 8.21, "amount": 249140611.0, "float_mkt": 4661535900.440001, "total_mkt": 6333998580.000001, "turnover": 5.43251895904541, "sealed_capital": 122649469.0, "first_seal_time": "093612", "last_seal_time": "093612", "explode_count": 0, "continuous": "1/1", "lb_count": 1, "sector": "照明设备"}, {"date": "20260316", "code": "600313", "name": "农发种业", "pct": 10.060606002807617, "price": 9.08, "amount": 1652427584.0, "float_mkt": 9826363860.04, "total_mkt": 10545275629.44, "turnover": 17.012407302856445, "sealed_capital": 75630952.0, "first_seal_time": "093913", "last_seal_time": "104925", "explode_count": 9, "continuous": "1/1", "lb_count": 1, "sector": "种植业"}, {"date": "20260316", "code": "001278", "name": "一彬科技", "pct": 9.991312026977539, "price": 25.32, "amount": 123952585.0, "float_mkt": 2160071380.32, "total_mkt": 3132929688.0, "turnover": 5.878108501434326, "sealed_capital": 133995136.0, "first_seal_time": "094424", "last_seal_time": "094424", "explode_count": 0, "continuous": "1/1", "lb_count": 1, "sector": "汽车零部"}, {"date": "20260316", "code": "603738", "name": "泰晶科技", "pct": 9.995654106140137, "price": 25.31, "amount": 1140182672.0, "float_mkt": 9766812422.52, "total_mkt": 9766812321.279999, "turnover": 11.971078872680664, "sealed_capital": 90398208.0, "first_seal_time": "094809", "last_seal_time": "131845", "explode_count": 1, "continuous": "1/1", "lb_count": 1, "sector": "元件"}, {"date": "20260316", "code": "603929", "name": "亚翔集成", "pct": 9.997870445251465, "price": 154.91, "amount": 1410204032.0, "float_mkt": 33051597600.0, "total_mkt": 33051597600.0, "turnover": 4.3436102867126465, "sealed_capital": 181178553.0, "first_seal_time": "094908", "last_seal_time": "101502", "explode_count": 1, "continuous": "2/2", "lb_count": 2, "sector": "专业工程"}, {"date": "20260316", "code": "000020", "name": "深华发Ａ", "pct": 10.006901741027832, "price": 15.94, "amount": 113245908.0, "float_mkt": 2887776332.54, "total_mkt": 4513590038.08, "turnover": 3.964749574661255, "sealed_capital": 62424228.0, "first_seal_time": "094939", "last_seal_time": "094939", "explode_count": 0, "continuous": "1/1", "lb_count": 1, "sector": "光学光电"}, {"date": "20260316", "code": "600545", "name": "卓郎智能", "pct": 9.921670913696289, "price": 4.21, "amount": 714124864.0, "float_mkt": 7527110454.62, "total_mkt": 7527110463.04, "turnover": 9.821280479431152, "sealed_capital": 58643952.0, "first_seal_time": "095636", "last_seal_time": "103327", "explode_count": 2, "continuous": "1/1", "lb_count": 1, "sector": "专用设备"}, {"date": "20260316", "code": "603421", "name": "鼎信通讯", "pct": 10.021322250366211, "price": 10.32, "amount": 859430640.0, "float_mkt": 6730606073.52, "total_mkt": 6730606083.84, "turnover": 13.144960403442383, "sealed_capital": 31639943.0, "first_seal_time": "095820", "last_seal_time": "110150", "explode_count": 1, "continuous": "5/3", "lb_count": 1, "sector": "通信设备"}, {"date": "20260316", "code": "000639", "name": "西王食品", "pct": 10.175437927246094, "price": 3.14, "amount": 340685056.0, "float_mkt": 3389400064.08, "total_mkt": 3389404221.44, "turnover": 10.323563575744629, "sealed_capital": 88731790.0, "first_seal_time": "095930", "last_seal_time": "095930", "explode_count": 0, "continuous": "1/1", "lb_count": 1, "sector": "食品加工"}, {"date": "20260316", "code": "002467", "name": "二六三", "pct": 9.941520690917969, "price": 7.52, "amount": 1593076496.0, "float_mkt": 10278967356.64, "total_mkt": 10342796477.439999, "turnover": 15.848691940307617, "sealed_capital": 131113275.0, "first_seal_time": "100030", "last_seal_time": "100909", "explode_count": 1, "continuous": "1/1", "lb_count": 1, "sector": "通信服务"}, {"date": "20260316", "code": "000533", "name": "顺钠股份", "pct": 10.023585319519043, "price": 18.66, "amount": 3585523088.0, "float_mkt": 12780278784.0, "total_mkt": 12890626560.0, "turnover": 29.589651107788086, "sealed_capital": 115752607.0, "first_seal_time": "100118", "last_seal_time": "101324", "explode_count": 4, "continuous": "9/5", "lb_count": 1, "sector": "电网设备"}, {"date": "20260316", "code": "605299", "name": "舒华体育", "pct": 9.968354225158691, "price": 13.9, "amount": 258589790.0, "float_mkt": 5688248669.7, "total_mkt": 5688248739.2, "turnover": 4.680033206939697, "sealed_capital": 111041470.0, "first_seal_time": "100157", "last_seal_time": "100157", "explode_count": 0, "continuous": "1/1", "lb_count": 1, "sector": "文娱用品"}, {"date": "20260316", "code": "600152", "name": "维科技术", "pct": 10.030706405639648, "price": 10.75, "amount": 646662144.0, "float_mkt": 5687603281.25, "total_mkt": 5687603292.0, "turnover": 11.884139060974121, "sealed_capital": 81377199.0, "first_seal_time": "100459", "last_seal_time": "100459", "explode_count": 0, "continuous": "1/1", "lb_count": 1, "sector": "电池"}, {"date": "20260316", "code": "002990", "name": "盛视科技", "pct": 9.992401123046875, "price": 28.95, "amount": 199557879.0, "float_mkt": 3882061482.6, "total_mkt": 7580619395.099999, "turnover": 5.278224945068359, "sealed_capital": 110032581.0, "first_seal_time": "100924", "last_seal_time": "100924", "explode_count": 0, "continuous": "1/1", "lb_count": 1, "sector": "计算机设"}, {"date": "20260316", "code": "300042", "name": "朗科科技", "pct": 20.0, "price": 45.6, "amount": 1540742480.0, "float_mkt": 9137398680.0, "total_mkt": 9138240000.0, "turnover": 18.023298263549805, "sealed_capital": 43231353.0, "first_seal_time": "101657", "last_seal_time": "102924", "explode_count": 2, "continuous": "1/1", "lb_count": 1, "sector": "计算机设"}, {"date": "20260316", "code": "603778", "name": "国晟科技", "pct": 10.00487995147705, "price": 22.54, "amount": 2113329392.0, "float_mkt": 14489999980.68, "total_mkt": 14800713565.119999, "turnover": 15.091817855834961, "sealed_capital": 102674208.0, "first_seal_time": "102018", "last_seal_time": "102618", "explode_count": 1, "continuous": "4/2", "lb_count": 1, "sector": "光伏设备"}, {"date": "20260316", "code": "600751", "name": "海航科技", "pct": 9.923664093017578, "price": 4.32, "amount": 553229744.0, "float_mkt": 11116176704.640001, "total_mkt": 12525139192.320002, "turnover": 5.121127605438232, "sealed_capital": 54692496.0, "first_seal_time": "103227", "last_seal_time": "103227", "explode_count": 0, "continuous": "1/1", "lb_count": 1, "sector": "航运港口"}, {"date": "20260316", "code": "002426", "name": "胜利精密", "pct": 10.098522186279297, "price": 4.47, "amount": 2194454672.0, "float_mkt": 15209621512.769999, "total_mkt": 15209737862.4, "turnover": 14.832886695861816, "sealed_capital": 159464568.0, "first_seal_time": "105427", "last_seal_time": "105427", "explode_count": 0, "continuous": "1/1", "lb_count": 1, "sector": "消费电子"}, {"date": "20260316", "code": "002636", "name": "金安国纪", "pct": 10.0172119140625, "price": 31.96, "amount": 1507037408.0, "float_mkt": 23149120727.32, "total_mkt": 23266880000.0, "turnover": 6.8740034103393555, "sealed_capital": 149885368.0, "first_seal_time": "105606", "last_seal_time": "105606", "explode_count": 0, "continuous": "1/1", "lb_count": 1, "sector": "元件"}, {"date": "20260316", "code": "000620", "name": "盈新发展", "pct": 9.966776847839355, "price": 3.31, "amount": 1051506512.0, "float_mkt": 15463488577.65, "total_mkt": 19435708206.08, "turnover": 7.0580058097839355, "sealed_capital": 153539626.0, "first_seal_time": "112024", "last_seal_time": "112024", "explode_count": 0, "continuous": "1/1", "lb_count": 1, "sector": "房地产开"}, {"date": "20260316", "code": "600667", "name": "太极实业", "pct": 9.9609375, "price": 11.26, "amount": 2393492208.0, "float_mkt": 23550764924.28, "total_mkt": 23550764901.76, "turnover": 10.568775177001953, "sealed_capital": 184813679.0, "first_seal_time": "112407", "last_seal_time": "112407", "explode_count": 0, "continuous": "1/1", "lb_count": 1, "sector": "工程咨询"}, {"date": "20260316", "code": "605366", "name": "宏柏新材", "pct": 9.989806175231934, "price": 10.79, "amount": 560313392.0, "float_mkt": 7818407942.15, "total_mkt": 7818407931.36, "turnover": 7.508786201477051, "sealed_capital": 118186549.0, "first_seal_time": "130149", "last_seal_time": "130149", "explode_count": 0, "continuous": "1/1", "lb_count": 1, "sector": "化学制品"}, {"date": "20260316", "code": "601975", "name": "招商南油", "pct": 10.068650245666504, "price": 4.81, "amount": 2572568624.0, "float_mkt": 22512457901.179996, "total_mkt": 22512457410.559998, "turnover": 11.816990852355957, "sealed_capital": 30642874.0, "first_seal_time": "130532", "last_seal_time": "133044", "explode_count": 7, "continuous": "1/1", "lb_count": 1, "sector": "航运港口"}, {"date": "20260316", "code": "002995", "name": "天地在线", "pct": 9.991119384765625, "price": 24.77, "amount": 483185760.0, "float_mkt": 2784574242.16, "total_mkt": 4395547469.6, "turnover": 17.97272491455078, "sealed_capital": 174543291.0, "first_seal_time": "130851", "last_seal_time": "130851", "explode_count": 0, "continuous": "1/1", "lb_count": 1, "sector": "广告营销"}, {"date": "20260316", "code": "002980", "name": "华盛昌", "pct": 9.988616943359375, "price": 38.65, "amount": 519962640.0, "float_mkt": 3918721335.6, "total_mkt": 7320354834.0, "turnover": 13.804189682006836, "sealed_capital": 109725804.0, "first_seal_time": "131739", "last_seal_time": "131739", "explode_count": 0, "continuous": "1/1", "lb_count": 1, "sector": "电网设备"}, {"date": "20260316", "code": "603986", "name": "兆易创新", "pct": 9.998922348022461, "price": 306.16, "amount": 13600507648.0, "float_mkt": 204467359681.76, "total_mkt": 214649525479.68002, "turnover": 6.928790092468262, "sealed_capital": 747202461.0, "first_seal_time": "132534", "last_seal_time": "133601", "explode_count": 1, "continuous": "1/1", "lb_count": 1, "sector": "半导体"}, {"date": "20260316", "code": "300606", "name": "金太阳", "pct": 20.005891799926758, "price": 40.73, "amount": 895933152.0, "float_mkt": 4792881814.78, "total_mkt": 5634906952.98, "turnover": 20.0333309173584, "sealed_capital": 153805888.0, "first_seal_time": "132803", "last_seal_time": "132803", "explode_count": 0, "continuous": "1/1", "lb_count": 1, "sector": "通用设备"}, {"date": "20260316", "code": "603052", "name": "可川科技", "pct": 10.0, "price": 64.13, "amount": 602739184.0, "float_mkt": 12049852694.66, "total_mkt": 12049852694.66, "turnover": 5.275407314300537, "sealed_capital": 107101973.0, "first_seal_time": "135714", "last_seal_time": "135714", "explode_count": 0, "continuous": "1/1", "lb_count": 1, "sector": "消费电子"}, {"date": "20260316", "code": "000890", "name": "法尔胜", "pct": 10.009016990661621, "price": 12.2, "amount": 1531178816.0, "float_mkt": 5117790761.2, "total_mkt": 5117948409.599999, "turnover": 31.123615264892578, "sealed_capital": 2543700.0, "first_seal_time": "140833", "last_seal_time": "145554", "explode_count": 4, "continuous": "16/9", "lb_count": 3, "sector": "环保设备"}, {"date": "20260316", "code": "603175", "name": "超颖电子", "pct": 10.003742218017578, "price": 88.19, "amount": 693139920.0, "float_mkt": 3880298972.52, "total_mkt": 38541616436.32, "turnover": 18.873132705688477, "sealed_capital": 59007047.0, "first_seal_time": "141347", "last_seal_time": "141347", "explode_count": 0, "continuous": "1/1", "lb_count": 1, "sector": "元件"}, {"date": "20260316", "code": "002235", "name": "安妮股份", "pct": 9.990485191345215, "price": 11.56, "amount": 998810160.0, "float_mkt": 6399365171.12, "total_mkt": 6699855649.280001, "turnover": 16.18146324157715, "sealed_capital": 128256708.0, "first_seal_time": "142139", "last_seal_time": "142139", "explode_count": 0, "continuous": "1/1", "lb_count": 1, "sector": "造纸"}, {"date": "20260316", "code": "300051", "name": "琏升科技", "pct": 19.956850051879883, "price": 11.12, "amount": 668063376.0, "float_mkt": 4088557286.7999997, "total_mkt": 4136836779.5199995, "turnover": 17.544658660888672, "sealed_capital": 108483384.0, "first_seal_time": "144339", "last_seal_time": "144339", "explode_count": 0, "continuous": "1/1", "lb_count": 1, "sector": "光伏设备"}, {"date": "20260316", "code": "603248", "name": "锡华科技", "pct": 10.0, "price": 31.02, "amount": 1179755408.0, "float_mkt": 2149962636.36, "total_mkt": 14269200000.0, "turnover": 57.86622619628906, "sealed_capital": 54907664.0, "first_seal_time": "144621", "last_seal_time": "144715", "explode_count": 1, "continuous": "2/2", "lb_count": 2, "sector": "风电设备"}, {"date": "20260316", "code": "002831", "name": "裕同科技", "pct": 10.011573791503906, "price": 38.02, "amount": 1317657232.0, "float_mkt": 19427962186.38, "total_mkt": 34997923422.08, "turnover": 7.3264594078063965, "sealed_capital": 18511709.0, "first_seal_time": "145509", "last_seal_time": "145509", "explode_count": 0, "continuous": "4/2", "lb_count": 1, "sector": "包装印刷"}]