{"2026-01-16": {"open": 11.66, "close": 12.4, "high": 12.75, "low": 11.57, "vol": 224825.0}, "2026-01-19": {"open": 12.38, "close": 12.88, "high": 12.9, "low": 12.28, "vol": 190573.0}, "2026-01-20": {"open": 12.8, "close": 12.82, "high": 12.88, "low": 12.48, "vol": 142201.0}, "2026-01-21": {"open": 12.88, "close": 13.08, "high": 13.6, "low": 12.81, "vol": 159209.0}, "2026-01-22": {"open": 13.09, "close": 13.27, "high": 13.49, "low": 12.92, "vol": 156941.0}, "2026-01-23": {"open": 13.54, "close": 13.79, "high": 13.81, "low": 13.0, "vol": 201793.0}, "2026-01-26": {"open": 13.79, "close": 12.97, "high": 13.94, "low": 12.7, "vol": 219997.0}, "2026-01-27": {"open": 13.04, "close": 12.86, "high": 13.32, "low": 12.45, "vol": 150906.0}, "2026-01-28": {"open": 12.83, "close": 12.5, "high": 12.86, "low": 12.38, "vol": 119744.0}, "2026-01-29": {"open": 12.56, "close": 12.22, "high": 12.56, "low": 12.18, "vol": 127661.0}, "2026-01-30": {"open": 12.22, "close": 13.04, "high": 13.2, "low": 12.08, "vol": 182206.0}, "2026-02-02": {"open": 13.0, "close": 12.78, "high": 13.15, "low": 12.46, "vol": 174385.0}, "2026-02-03": {"open": 12.93, "close": 12.81, "high": 12.98, "low": 12.68, "vol": 108680.0}, "2026-02-04": {"open": 12.89, "close": 13.42, "high": 13.65, "low": 12.81, "vol": 171885.0}, "2026-02-05": {"open": 13.53, "close": 14.76, "high": 14.76, "low": 13.31, "vol": 144938.0}, "2026-02-06": {"open": 14.62, "close": 13.62, "high": 14.62, "low": 13.41, "vol": 376755.0}, "2026-02-09": {"open": 13.62, "close": 14.05, "high": 14.47, "low": 13.62, "vol": 247726.0}, "2026-02-10": {"open": 14.11, "close": 14.55, "high": 14.73, "low": 13.9, "vol": 194888.0}, "2026-02-11": {"open": 14.54, "close": 14.85, "high": 15.1, "low": 14.4, "vol": 222756.0}, "2026-02-12": {"open": 14.75, "close": 14.51, "high": 14.84, "low": 14.18, "vol": 150816.0}, "2026-02-13": {"open": 14.35, "close": 15.16, "high": 15.35, "low": 14.3, "vol": 200366.0}, "2026-02-24": {"open": 15.26, "close": 14.8, "high": 15.99, "low": 14.79, "vol": 179644.0}, "2026-02-25": {"open": 14.8, "close": 15.42, "high": 15.48, "low": 14.61, "vol": 149171.0}, "2026-02-26": {"open": 15.47, "close": 15.66, "high": 16.54, "low": 15.4, "vol": 189039.0}, "2026-02-27": {"open": 15.73, "close": 16.09, "high": 16.28, "low": 15.41, "vol": 223059.0}, "2026-03-02": {"open": 15.85, "close": 15.41, "high": 15.92, "low": 15.22, "vol": 211120.0}, "2026-03-03": {"open": 15.38, "close": 14.58, "high": 15.5, "low": 14.55, "vol": 185095.0}, "2026-03-04": {"open": 14.45, "close": 16.04, "high": 16.04, "low": 14.33, "vol": 226246.0}, "2026-03-05": {"open": 15.84, "close": 16.09, "high": 16.46, "low": 15.5, "vol": 309408.0}, "2026-03-06": {"open": 16.26, "close": 16.17, "high": 16.26, "low": 15.71, "vol": 143639.0}, "2026-03-09": {"open": 15.96, "close": 15.71, "high": 16.12, "low": 15.31, "vol": 153848.0}, "2026-03-10": {"open": 15.91, "close": 15.72, "high": 16.22, "low": 15.4, "vol": 126996.0}, "2026-03-11": {"open": 15.74, "close": 15.21, "high": 15.78, "low": 15.16, "vol": 112463.0}, "2026-03-12": {"open": 15.1, "close": 15.44, "high": 15.84, "low": 15.06, "vol": 122468.0}, "2026-03-13": {"open": 15.25, "close": 15.7, "high": 15.8, "low": 15.19, "vol": 108620.0}, "2026-03-16": {"open": 15.44, "close": 14.9, "high": 15.55, "low": 14.6, "vol": 140851.0}, "2026-03-17": {"open": 15.27, "close": 14.82, "high": 15.38, "low": 14.82, "vol": 96688.0}, "2026-03-18": {"open": 14.89, "close": 14.91, "high": 15.03, "low": 14.48, "vol": 90094.0}, "2026-03-19": {"open": 14.99, "close": 14.43, "high": 14.99, "low": 14.31, "vol": 91052.0}, "2026-03-20": {"open": 14.45, "close": 14.5, "high": 14.97, "low": 14.4, "vol": 83343.0}}