{"2026-01-16": {"open": 6.46, "close": 6.33, "high": 6.47, "low": 6.24, "vol": 219688.0}, "2026-01-19": {"open": 6.32, "close": 6.39, "high": 6.64, "low": 6.22, "vol": 344044.0}, "2026-01-20": {"open": 6.34, "close": 6.26, "high": 6.43, "low": 6.21, "vol": 239845.0}, "2026-01-21": {"open": 6.2, "close": 6.22, "high": 6.26, "low": 6.16, "vol": 159061.0}, "2026-01-22": {"open": 6.23, "close": 6.26, "high": 6.28, "low": 6.18, "vol": 131800.0}, "2026-01-23": {"open": 6.25, "close": 6.32, "high": 6.32, "low": 6.22, "vol": 165206.0}, "2026-01-26": {"open": 6.32, "close": 6.95, "high": 6.95, "low": 6.21, "vol": 836284.0}, "2026-01-27": {"open": 6.96, "close": 6.89, "high": 7.04, "low": 6.68, "vol": 976437.0}, "2026-01-28": {"open": 6.94, "close": 7.11, "high": 7.58, "low": 6.88, "vol": 1293886.0}, "2026-01-29": {"open": 6.92, "close": 7.4, "high": 7.5, "low": 6.85, "vol": 1191980.0}, "2026-01-30": {"open": 7.16, "close": 7.2, "high": 7.39, "low": 6.9, "vol": 864192.0}, "2026-02-02": {"open": 7.31, "close": 7.92, "high": 7.92, "low": 7.2, "vol": 1090154.0}, "2026-02-03": {"open": 7.7, "close": 8.11, "high": 8.7, "low": 7.55, "vol": 1848653.0}, "2026-02-04": {"open": 7.88, "close": 7.33, "high": 8.07, "low": 7.3, "vol": 1317094.0}, "2026-02-05": {"open": 7.13, "close": 8.06, "high": 8.06, "low": 7.13, "vol": 827604.0}, "2026-02-06": {"open": 7.81, "close": 7.87, "high": 8.11, "low": 7.56, "vol": 1097513.0}, "2026-02-09": {"open": 7.86, "close": 8.02, "high": 8.18, "low": 7.86, "vol": 962423.0}, "2026-02-10": {"open": 7.95, "close": 8.3, "high": 8.45, "low": 7.9, "vol": 1224468.0}, "2026-02-11": {"open": 8.1, "close": 8.18, "high": 8.67, "low": 8.08, "vol": 1154662.0}, "2026-02-12": {"open": 8.22, "close": 7.89, "high": 8.44, "low": 7.86, "vol": 913854.0}, "2026-02-13": {"open": 7.89, "close": 7.6, "high": 8.2, "low": 7.56, "vol": 700216.0}, "2026-02-24": {"open": 7.75, "close": 7.49, "high": 7.85, "low": 7.39, "vol": 503594.0}, "2026-02-25": {"open": 7.58, "close": 7.89, "high": 8.24, "low": 7.49, "vol": 1160684.0}, "2026-02-26": {"open": 7.78, "close": 7.89, "high": 8.15, "low": 7.63, "vol": 1020435.0}, "2026-02-27": {"open": 7.75, "close": 8.03, "high": 8.24, "low": 7.69, "vol": 788168.0}, "2026-03-02": {"open": 7.76, "close": 7.58, "high": 7.83, "low": 7.33, "vol": 764895.0}, "2026-03-03": {"open": 7.5, "close": 6.93, "high": 7.66, "low": 6.9, "vol": 650160.0}, "2026-03-04": {"open": 6.77, "close": 6.93, "high": 7.03, "low": 6.7, "vol": 343866.0}, "2026-03-05": {"open": 7.07, "close": 7.09, "high": 7.19, "low": 6.91, "vol": 358301.0}, "2026-03-06": {"open": 7.0, "close": 7.29, "high": 7.55, "low": 6.97, "vol": 475363.0}, "2026-03-09": {"open": 7.23, "close": 8.02, "high": 8.02, "low": 7.17, "vol": 978454.0}, "2026-03-10": {"open": 8.2, "close": 8.82, "high": 8.82, "low": 7.99, "vol": 1698664.0}, "2026-03-11": {"open": 9.3, "close": 8.51, "high": 9.59, "low": 8.45, "vol": 2188203.0}, "2026-03-12": {"open": 8.71, "close": 8.45, "high": 8.82, "low": 8.36, "vol": 1331564.0}, "2026-03-13": {"open": 8.36, "close": 7.91, "high": 8.46, "low": 7.85, "vol": 995242.0}, "2026-03-16": {"open": 7.91, "close": 8.09, "high": 8.45, "low": 7.64, "vol": 979961.0}, "2026-03-17": {"open": 8.2, "close": 8.53, "high": 8.89, "low": 7.95, "vol": 1577624.0}, "2026-03-18": {"open": 8.67, "close": 8.7, "high": 8.85, "low": 8.51, "vol": 1258894.0}, "2026-03-19": {"open": 8.55, "close": 8.53, "high": 8.85, "low": 8.38, "vol": 968385.0}, "2026-03-20": {"open": 8.58, "close": 8.0, "high": 8.69, "low": 7.99, "vol": 834089.0}}