{"2026-01-16": {"open": 10.7, "close": 10.71, "high": 10.76, "low": 10.61, "vol": 124973.0}, "2026-01-19": {"open": 10.72, "close": 10.72, "high": 10.82, "low": 10.68, "vol": 126329.0}, "2026-01-20": {"open": 10.74, "close": 10.48, "high": 10.74, "low": 10.42, "vol": 147263.0}, "2026-01-21": {"open": 10.41, "close": 10.69, "high": 10.69, "low": 10.37, "vol": 147837.0}, "2026-01-22": {"open": 10.73, "close": 10.75, "high": 10.76, "low": 10.61, "vol": 113763.0}, "2026-01-23": {"open": 10.77, "close": 10.88, "high": 10.9, "low": 10.72, "vol": 172854.0}, "2026-01-26": {"open": 10.94, "close": 10.7, "high": 10.98, "low": 10.57, "vol": 148664.0}, "2026-01-27": {"open": 10.61, "close": 10.92, "high": 10.99, "low": 10.36, "vol": 258260.0}, "2026-01-28": {"open": 10.9, "close": 10.64, "high": 10.91, "low": 10.59, "vol": 183083.0}, "2026-01-29": {"open": 10.59, "close": 10.32, "high": 10.61, "low": 10.28, "vol": 174628.0}, "2026-01-30": {"open": 10.31, "close": 10.36, "high": 10.46, "low": 10.17, "vol": 119619.0}, "2026-02-02": {"open": 10.13, "close": 10.82, "high": 11.35, "low": 10.07, "vol": 430992.0}, "2026-02-03": {"open": 10.86, "close": 10.88, "high": 10.97, "low": 10.7, "vol": 217972.0}, "2026-02-04": {"open": 10.88, "close": 11.09, "high": 11.19, "low": 10.81, "vol": 227515.0}, "2026-02-05": {"open": 11.18, "close": 10.84, "high": 11.22, "low": 10.83, "vol": 128381.0}, "2026-02-06": {"open": 10.8, "close": 10.97, "high": 11.09, "low": 10.7, "vol": 162349.0}, "2026-02-09": {"open": 11.13, "close": 10.99, "high": 11.18, "low": 10.92, "vol": 128877.0}, "2026-02-10": {"open": 10.95, "close": 10.93, "high": 11.09, "low": 10.92, "vol": 98614.0}, "2026-02-11": {"open": 10.87, "close": 10.96, "high": 11.03, "low": 10.87, "vol": 96022.0}, "2026-02-12": {"open": 11.0, "close": 10.97, "high": 11.17, "low": 10.96, "vol": 149736.0}, "2026-02-13": {"open": 10.97, "close": 10.92, "high": 11.04, "low": 10.9, "vol": 95154.0}, "2026-02-24": {"open": 11.04, "close": 10.94, "high": 11.05, "low": 10.81, "vol": 94783.0}, "2026-02-25": {"open": 10.99, "close": 10.99, "high": 11.05, "low": 10.92, "vol": 99881.0}, "2026-02-26": {"open": 11.07, "close": 11.09, "high": 11.16, "low": 10.97, "vol": 161169.0}, "2026-02-27": {"open": 11.06, "close": 10.76, "high": 11.08, "low": 10.75, "vol": 198746.0}, "2026-03-02": {"open": 10.51, "close": 10.44, "high": 10.74, "low": 10.41, "vol": 154088.0}, "2026-03-03": {"open": 10.49, "close": 9.87, "high": 10.55, "low": 9.8, "vol": 183025.0}, "2026-03-04": {"open": 9.75, "close": 9.77, "high": 9.97, "low": 9.66, "vol": 112862.0}, "2026-03-05": {"open": 9.91, "close": 9.96, "high": 10.09, "low": 9.91, "vol": 98823.0}, "2026-03-06": {"open": 9.98, "close": 10.96, "high": 10.96, "low": 9.94, "vol": 269236.0}, "2026-03-09": {"open": 10.96, "close": 11.17, "high": 11.21, "low": 10.88, "vol": 484526.0}, "2026-03-10": {"open": 11.29, "close": 11.14, "high": 11.29, "low": 11.06, "vol": 255735.0}, "2026-03-11": {"open": 11.29, "close": 12.25, "high": 12.25, "low": 11.2, "vol": 739974.0}, "2026-03-12": {"open": 12.0, "close": 12.71, "high": 13.04, "low": 11.88, "vol": 956635.0}, "2026-03-13": {"open": 12.52, "close": 12.8, "high": 13.34, "low": 12.5, "vol": 560959.0}, "2026-03-16": {"open": 12.8, "close": 12.41, "high": 12.8, "low": 12.09, "vol": 442093.0}, "2026-03-17": {"open": 12.63, "close": 11.86, "high": 12.64, "low": 11.8, "vol": 350799.0}, "2026-03-18": {"open": 11.85, "close": 12.45, "high": 12.96, "low": 11.85, "vol": 509178.0}, "2026-03-19": {"open": 12.11, "close": 12.4, "high": 12.62, "low": 11.96, "vol": 397981.0}, "2026-03-20": {"open": 12.54, "close": 11.62, "high": 12.55, "low": 11.6, "vol": 339263.0}}